dbtgenlib/__init__.py
dbtgenlib/gendoc.py
dbtgenlib/genyml.py
dbtgenlib/testkeys.py
dbtgenlib-0.0.39.dist-info/LICENSE
dbtgenlib-0.0.39.dist-info/METADATA
dbtgenlib-0.0.39.dist-info/WHEEL
dbtgenlib-0.0.39.dist-info/entry_points.txt
dbtgenlib-0.0.39.dist-info/top_level.txt
dbtgenlib-0.0.39.dist-info/RECORD
